odoo/addons/crowdfunding_demo/README.rst
odoo/addons/crowdfunding_demo/__init__.py
odoo/addons/crowdfunding_demo/__manifest__.py
odoo/addons/crowdfunding_demo/demo/payment_acquirer.xml
odoo/addons/crowdfunding_demo/demo/res_company.xml
odoo/addons/crowdfunding_demo/i18n/crowdfunding_demo.pot
odoo/addons/crowdfunding_demo/i18n/it.po
odoo/addons/crowdfunding_demo/readme/CONTRIBUTORS.md
odoo/addons/crowdfunding_demo/readme/DESCRIPTION.md
odoo/addons/crowdfunding_demo/readme/USAGE.md
odoo/addons/crowdfunding_demo/static/description/icon.png
odoo/addons/crowdfunding_demo/static/description/index.html
odoo14_addon_crowdfunding_demo-14.0.1.0.1.dev4.dist-info/METADATA
odoo14_addon_crowdfunding_demo-14.0.1.0.1.dev4.dist-info/WHEEL
odoo14_addon_crowdfunding_demo-14.0.1.0.1.dev4.dist-info/top_level.txt
odoo14_addon_crowdfunding_demo-14.0.1.0.1.dev4.dist-info/RECORD
