Metadata-Version: 2.1
Name: odoo14-addon-crowdfunding_demo
Version: 14.0.1.0.1.dev4
Summary: Installs demo data to have crowdfunding up and running on runbot
Home-page: https://github.com/OCA/crowdfunding
Author: Hunki Enterprises BV, Odoo Community Association (OCA)
Author-email: support@odoo-community.org
License: AGPL-3
Classifier: Programming Language :: Python
Classifier: Framework :: Odoo
Classifier: Framework :: Odoo :: 14.0
Classifier: License :: OSI Approved :: GNU Affero General Public License v3
Classifier: Development Status :: 3 - Alpha
Requires-Python: >=3.6
Requires-Dist: odoo14-addon-crowdfunding
Requires-Dist: odoo<14.1dev,>=14.0a
